mxlm/__info__.py
mxlm/__init__.py
mxlm/api_proxy.py
mxlm/chat_api.py
mxlm/chatmd_utils.py
mxlm/dialog_format_conversion.py
mxlm/mxlm_utils.py
mxlm/openai_requests.py
mxlm/prefill_logprobs.py
mxlm/random_utils.py
mxlm/richtext.py
mxlm/tmp_api_proxy_copilot.py
mxlm-0.2.3.dist-info/METADATA
mxlm-0.2.3.dist-info/WHEEL
mxlm-0.2.3.dist-info/top_level.txt
mxlm-0.2.3.dist-info/RECORD
