Metadata-Version: 2.4
Name: mxlm
Version: 0.2.3
Summary: Language Model Utils
Home-page: https://github.com/magic-python-toolbox/mxlm
Author: DIYer22
Author-email: ylxx@live.com
Classifier: Topic :: Software Development :: Libraries :: Python Modules
Classifier: Programming Language :: Python :: 3
Classifier: License :: OSI Approved :: MIT License
Classifier: Operating System :: OS Independent
Dynamic: author
Dynamic: author-email
Dynamic: classifier
Dynamic: description
Dynamic: description-content-type
Dynamic: home-page
Dynamic: summary
